README.md
setup.py
communities/__init__.py
communities/utilities.py
communities.egg-info/PKG-INFO
communities.egg-info/SOURCES.txt
communities.egg-info/dependency_links.txt
communities.egg-info/requires.txt
communities.egg-info/top_level.txt
communities/algorithms/__init__.py
communities/algorithms/bron_kerbosch.py
communities/algorithms/girvan_newman.py
communities/algorithms/hierarchical_clustering.py
communities/algorithms/louvain_method.py
communities/algorithms/spectral_clustering.py
communities/visualization/__init__.py
communities/visualization/draw_communities.py
communities/visualization/louvain_animation.py