Metadata-Version: 2.1
Name: communities
Version: 3.0.0
Summary: Library for detecting community structure in graphs
Home-page: https://github.com/shobrook/communities
Author: shobrook
Author-email: shobrookj@gmail.com
License: MIT
Keywords: graph,louvain,community,clustering,detection,girvan-newman,hierarchical,visualization
Platform: UNKNOWN
Requires-Python: >=3
